{
  "main": {
    "id": "dc99ae558d0d1abb",
    "type": "split",
    "children": [
      {
        "id": "22612fe212bb5bdf",
        "type": "tabs",
        "children": [
          {
            "id": "bfaad3003878f62e",
            "type": "leaf",
            "state": {
              "type": "markdown",
              "state": {
                "file": "docs/advance/Github.md",
                "mode": "source",
                "source": false
              }
            }
          }
        ]
      }
    ],
    "direction": "vertical"
  },
  "left": {
    "id": "a5b924c46527103c",
    "type": "split",
    "children": [
      {
        "id": "46015ae92dbf23a5",
        "type": "tabs",
        "dimension": 66.72212978369384,
        "children": [
          {
            "id": "77d6edc82ddabe77",
            "type": "leaf",
            "state": {
              "type": "search",
              "state": {
                "query": "",
                "matchingCase": false,
                "explainSearch": false,
                "collapseAll": false,
                "extraContext": false,
                "sortOrder": "alphabetical"
              }
            }
          },
          {
            "id": "0778701f3cebc650",
            "type": "leaf",
            "state": {
              "type": "file-explorer",
              "state": {
                "sortOrder": "alphabetical"
              }
            }
          },
          {
            "id": "23e566189e642065",
            "type": "leaf",
            "state": {
              "type": "git-view",
              "state": {}
            }
          },
          {
            "id": "27f0f2b5e95a8868",
            "type": "leaf",
            "state": {
              "type": "bookmarks",
              "state": {}
            }
          },
          {
            "id": "206dc7a6048fcea4",
            "type": "leaf",
            "state": {
              "type": "outline",
              "state": {
                "file": "docs/advance/Github.md"
              }
            }
          },
          {
            "id": "3eab4a20cacd4769",
            "type": "leaf",
            "state": {
              "type": "surfing-tab-tree",
              "state": {}
            }
          }
        ],
        "currentTab": 1
      },
      {
        "id": "b406ae98ecade2d0",
        "type": "tabs",
        "dimension": 33.277870216306155,
        "children": [
          {
            "id": "2c4c3257d5f41c18",
            "type": "leaf",
            "state": {
              "type": "recent-files",
              "state": {}
            }
          }
        ]
      }
    ],
    "direction": "horizontal",
    "width": 300
  },
  "right": {
    "id": "b9a65f27b182d6e5",
    "type": "split",
    "children": [
      {
        "id": "758fed9daaee2c66",
        "type": "tabs",
        "children": [
          {
            "id": "4376e134b1d61037",
            "type": "leaf",
            "state": {
              "type": "tag",
              "state": {
                "sortOrder": "frequency",
                "useHierarchy": true
              }
            }
          },
          {
            "id": "8c352e004316ed0b",
            "type": "leaf",
            "state": {
              "type": "calendar",
              "state": {}
            }
          }
        ],
        "currentTab": 1
      },
      {
        "id": "5487b7e39b365947",
        "type": "tabs",
        "children": [
          {
            "id": "1e0f641ad6efdb03",
            "type": "leaf",
            "state": {
              "type": "backlink",
              "state": {
                "file": "docs/advance/Github.md",
                "collapseAll": false,
                "extraContext": false,
                "sortOrder": "alphabetical",
                "showSearch": false,
                "searchQuery": "",
                "backlinkCollapsed": false,
                "unlinkedCollapsed": true
              }
            }
          },
          {
            "id": "214927c8278c5685",
            "type": "leaf",
            "state": {
              "type": "outgoing-link",
              "state": {
                "file": "docs/advance/Github.md",
                "linksCollapsed": false,
                "unlinkedCollapsed": true
              }
            }
          }
        ]
      }
    ],
    "direction": "horizontal",
    "width": 300,
    "collapsed": true
  },
  "left-ribbon": {
    "hiddenItems": {
      "surfing:surfing-bookmark-manager": false,
      "dbfolder:创建一个新数据库表": true,
      "templater-obsidian:Templater": true,
      "switcher:打开快速切换": true,
      "graph:查看关系图谱": false,
      "canvas:新建白板": true,
      "daily-notes:打开/创建今天的日记": true,
      "templates:插入模板": true,
      "command-palette:打开命令面板": true,
      "obsidian42-brat:BRAT": true,
      "workspaces:管理工作区布局": false
    }
  },
  "active": "bfaad3003878f62e",
  "lastOpenFiles": [
    "docs/advance/Github.md",
    "node_modules/string.prototype.trim/LICENSE",
    "node_modules/string.prototype.trim/README.md",
    "node_modules/string.prototype.trim/shim.js",
    "node_modules/string.prototype.trim/polyfill.js",
    "docs 2/blog/assets",
    "docs 2/public/logo.png",
    "docs 2/blog/QuantumultX配置.md",
    "docs 2/public/favicon.ico",
    "docs 2/blog/Mac.md",
    "docs 2/public/logo.ico",
    "docs 2/public/developer.gif",
    "docs 2/wiki",
    "docs 2/blog",
    "docs 2/index.md",
    "docs 2/public",
    "docs 2",
    "node_modules 2/gitalk/src/assets/icon/tip.svg",
    "node_modules 2/gitalk/src/assets/icon/reply.svg",
    "node_modules 2/gitalk/src/assets/icon/heart_on.svg",
    "node_modules 2/gitalk/src/assets/icon/heart.svg",
    "node_modules 2/gitalk/src/assets/icon/github.svg",
    "node_modules 2/gitalk/src/assets/icon/arrow_down.svg",
    "node_modules 2/gitalk/src/assets/icon/edit.svg",
    "node_modules 2/gitalk/node_modules/react-flip-move/src/CODE_TOUR.md",
    "node_modules 2/@vueuse/shared/node_modules/vue-demi/README.md",
    "node_modules 2/@vueuse/core/node_modules/vue-demi/README.md",
    "node_modules 2/@vueuse/integrations/node_modules/vue-demi/README.md",
    "node_modules 2/gitalk/node_modules/react-flip-move/README.md",
    "node_modules 2/gitalk/node_modules/react-flip-move/LICENSE.md",
    "node_modules 2/gitalk/node_modules/react-dom/README.md",
    "node_modules 2/gitalk/node_modules/react/README.md",
    "node_modules 2/gitalk/node_modules/preact/README.md",
    "node_modules 2/axios/lib/helpers/README.md",
    "node_modules 2/axios/lib/core/README.md",
    "node_modules 2/axios/lib/adapters/README.md",
    "node_modules 2/vitepress/template/markdown-examples.md",
    "node_modules 2/vitepress/template/index.md",
    "node_modules 2/vitepress/template/api-examples.md",
    "node_modules 2/date-fns/docs/webpack.md",
    "node_modules 2/date-fns/docs/unicodeTokens.md",
    "node_modules 2/date-fns/docs/upgradeGuide.md",
    "node_modules 2/date-fns/docs/timeZones.md",
    "node_modules 2/date-fns/docs/logotype.svg",
    "node_modules 2/date-fns/docs/i18nContributionGuide.md",
    "node_modules 2/date-fns/docs/i18n.md",
    "home.canvas"
  ]
}