{
  "confirmDeletion": false,
  "showAddCommand": false,
  "debug": false,
  "editorMenu": [],
  "fileMenu": [],
  "leftRibbon": [
    {
      "id": "workspace:move-to-new-window",
      "icon": "lucide-maximize",
      "name": "新窗口",
      "mode": "mobile"
    },
    {
      "id": "outline:open-for-current",
      "icon": "lucide-list",
      "name": "大纲",
      "mode": "mobile"
    }
  ],
  "rightRibbon": [],
  "titleBar": [],
  "statusBar": [],
  "pageHeader": [
    {
      "id": "workspace:toggle-pin",
      "icon": "lucide-pin",
      "name": "固定",
      "mode": "any",
      "color": "#000000"
    },
    {
      "id": "quickadd:runQuickAdd",
      "icon": "brush",
      "name": "QuickAdd",
      "mode": "any",
      "color": "#000000"
    },
    {
      "id": "file-explorer:reveal-active-file",
      "icon": "bus",
      "name": "定位当前文件",
      "mode": "any"
    },
    {
      "id": "editor:toggle-source",
      "icon": "lucide-code-2",
      "name": "切换实时阅览/源码模式",
      "mode": "any",
      "color": "#000000"
    },
    {
      "id": "app:delete-file",
      "icon": "lucide-trash-2",
      "name": "删除当前文件",
      "mode": "any"
    }
  ],
  "macros": [],
  "explorer": [],
  "hide": {
    "statusbar": [],
    "leftRibbon": []
  },
  "spacing": 8,
  "advancedToolbar": {
    "rowHeight": 48,
    "rowCount": 1,
    "spacing": 0,
    "buttonWidth": 48,
    "columnLayout": false,
    "mappedIcons": [],
    "tooltips": false,
    "heightOffset": 0
  }
}